ephem/stars.py
ephem/cities.py
ephem/__init__.py
ephem/_libastro.cpython-313-aarch64-linux-musl.so
ephem/tests/test_bodies.py
ephem/tests/test_satellite.py
ephem/tests/test_locales.py
ephem/tests/test_rise_set.py
ephem/tests/__init__.py
ephem/tests/test_github_issues.py
ephem/tests/test_launchpad_236872.py
ephem/tests/test_launchpad_244811.py
ephem/tests/test_constants.py
ephem/tests/test_usno_equinoxes.py
ephem/tests/test_observers.py
ephem/tests/test_mag.py
ephem/tests/test_stars.py
ephem/tests/test_rst.py
ephem/tests/test_jpl.py
ephem/tests/test_usno.py
ephem/tests/test_dates.py
ephem/tests/test_angles.py
ephem/tests/test_cities.py
ephem/tests/wulfgar.py
ephem/tests/jpl/saturn.txt
ephem/tests/jpl/mars.txt
ephem/tests/jpl/phobos.txt
ephem/tests/jpl/hyperion.txt
ephem/tests/jpl/oberon.txt
ephem/tests/jpl/uranus.txt
ephem/tests/jpl/jupiter.txt
ephem/tests/jpl/neptune.txt
ephem/tests/jpl/europa.txt
ephem/tests/usno/apptopo_moon.txt
ephem/tests/usno/apptopo_deneb.txt
ephem/tests/usno/apptopo_sun.txt
ephem/tests/usno/appgeo_moon.txt
ephem/tests/usno/astrom_antares.txt
ephem/tests/usno/appgeo_sun.txt
ephem/tests/usno/appgeo_jupiter.txt
ephem/tests/usno/moon_phases.txt
ephem/tests/usno/appgeo_deneb.txt
ephem/tests/usno/astrom_neptune.txt
ephem/tests/usno/risettran_rigel.txt
ephem/tests/usno/riset_sun.txt
ephem/tests/usno/riset_moon.txt
ephem/tests/usno/astrom_mercury.txt
ephem/tests/usno/risettran_moon.txt
ephem/doc/toc.rst
ephem/doc/newton.rst
ephem/doc/quick.rst
ephem/doc/catalogs.rst
ephem/doc/CHANGELOG.rst
ephem/doc/examples.rst
ephem/doc/index.rst
ephem/doc/radec.rst
ephem/doc/angle.rst
ephem/doc/date.rst
ephem/doc/tutorial.rst
ephem/doc/coordinates.rst
ephem/doc/rise-set.rst
ephem-4.2.dist-info/LICENSE
ephem-4.2.dist-info/WHEEL
ephem-4.2.dist-info/METADATA
ephem-4.2.dist-info/top_level.txt
ephem-4.2.dist-info/RECORD
