Metadata-Version: 2.1
Name: ephem
Version: 4.2
Summary: Compute positions of the planets and stars
Home-page: http://rhodesmill.org/pyephem/
Author: Brandon Rhodes
Author-email: brandon@rhodesmill.org
License: MIT
Project-URL: Source, https://github.com/brandon-rhodes/pyephem
Platform: UNKNOWN
Classifier: Development Status :: 6 - Mature
Classifier: Intended Audience :: Science/Research
Classifier: License :: OSI Approved :: MIT License
Classifier: Topic :: Scientific/Engineering :: Astronomy
Classifier: Programming Language :: Python :: 2
Classifier: Programming Language :: Python :: 2.6
Classifier: Programming Language :: Python :: 2.7
Classifier: Programming Language :: Python :: 3
Classifier: Programming Language :: Python :: 3.2
Classifier: Programming Language :: Python :: 3.3
Classifier: Programming Language :: Python :: 3.4
Classifier: Programming Language :: Python :: 3.5
Classifier: Programming Language :: Python :: 3.6
Classifier: Programming Language :: Python :: 3.7
Classifier: Programming Language :: Python :: 3.8
Classifier: Programming Language :: Python :: 3.9
Classifier: Programming Language :: Python :: 3.10
Classifier: Programming Language :: Python :: 3.11
Classifier: Programming Language :: Python :: 3.12
Classifier: Programming Language :: Python :: 3.13
License-File: LICENSE
